xacro2sdf/__init__.py
xacro2sdf/xacro2sdf.py
SDFUtils-1.0.0.dist-info/LICENSE
SDFUtils-1.0.0.dist-info/METADATA
SDFUtils-1.0.0.dist-info/WHEEL
SDFUtils-1.0.0.dist-info/top_level.txt
SDFUtils-1.0.0.dist-info/RECORD
