Metadata-Version: 2.1
Name: SDFUtils
Version: 1.0.0
Summary: Gazebo SDF utils - write smaller and simpler xacro and get richer and complex SDF files
Home-page: https://github.com/robobe/SDFUtils
Author: robobe, OSForLife
License: UNKNOWN
Platform: UNKNOWN
Classifier: Programming Language :: Python :: 3
Classifier: License :: OSI Approved :: GNU General Public License v3 (GPLv3)
Classifier: Operating System :: OS Independent
Requires-Python: >=3.5
